[
{ "source": {"x": 0, "y": 0.1069}, "target" : {"x": 2, "y": 0.1183} },
{ "source": {"x": 0, "y": 0.866}, "target" : {"x": 2, "y": 0.577} },
{ "source": {"x": 0, "y": 0.449}, "target" : {"x": 2, "y": 0.758} },
{ "source": {"x": 0, "y": 0.287}, "target" : {"x": 2, "y": 0.758} },
{ "source": {"x": 0, "y": 0.287}, "target" : {"x": 2, "y": 0.1501} },
{ "source": {"x": 0, "y": 0.542}, "target" : {"x": 2, "y": 0.758} },
{ "source": {"x": 0, "y": 0.692}, "target" : {"x": 2, "y": 0.758} },
{ "source": {"x": 0, "y": 0.455}, "target" : {"x": 2, "y": 0.761} },
{ "source": {"x": 0, "y": 0.455}, "target" : {"x": 2, "y": 0.1413} },
{ "source": {"x": 0, "y": 0.455}, "target" : {"x": 2, "y": 0.1003} },
{ "source": {"x": 0, "y": 0.831}, "target" : {"x": 2, "y": 0.761} },
{ "source": {"x": 0, "y": 0.831}, "target" : {"x": 2, "y": 0.1003} },
{ "source": {"x": 0, "y": 0.923}, "target" : {"x": 2, "y": 0.1301} },
{ "source": {"x": 0, "y": 0.812}, "target" : {"x": 2, "y": 0.1301} },
{ "source": {"x": 0, "y": 0.515}, "target" : {"x": 2, "y": 0.399} },
{ "source": {"x": 0, "y": 0.515}, "target" : {"x": 2, "y": 0.453} },
{ "source": {"x": 0, "y": 0.515}, "target" : {"x": 2, "y": 0.492} },
{ "source": {"x": 0, "y": 0.313}, "target" : {"x": 2, "y": 0.399} },
{ "source": {"x": 0, "y": 0.313}, "target" : {"x": 2, "y": 0.453} },
{ "source": {"x": 0, "y": 0.313}, "target" : {"x": 2, "y": 0.492} },
{ "source": {"x": 0, "y": 0.375}, "target" : {"x": 2, "y": 0.399} },
{ "source": {"x": 0, "y": 0.375}, "target" : {"x": 2, "y": 0.453} },
{ "source": {"x": 0, "y": 0.375}, "target" : {"x": 2, "y": 0.492} },
{ "source": {"x": 0, "y": 0.281}, "target" : {"x": 2, "y": 0.1080} },
{ "source": {"x": 0, "y": 0.1309}, "target" : {"x": 2, "y": 0.1351} },
{ "source": {"x": 0, "y": 0.176}, "target" : {"x": 2, "y": 0.275} },
{ "source": {"x": 0, "y": 0.554}, "target" : {"x": 2, "y": 0.604} },
{ "source": {"x": 0, "y": 0.554}, "target" : {"x": 2, "y": 0.684} },
{ "source": {"x": 0, "y": 0.554}, "target" : {"x": 2, "y": 0.480} },
{ "source": {"x": 0, "y": 0.166}, "target" : {"x": 2, "y": 0.480} },
{ "source": {"x": 0, "y": 0.166}, "target" : {"x": 2, "y": 0.604} },
{ "source": {"x": 0, "y": 0.166}, "target" : {"x": 2, "y": 0.684} },
{ "source": {"x": 0, "y": 0.166}, "target" : {"x": 2, "y": 0.863} },
{ "source": {"x": 0, "y": 0.345}, "target" : {"x": 2, "y": 0.361} },
{ "source": {"x": 0, "y": 0.590}, "target" : {"x": 2, "y": 0.1255} },
{ "source": {"x": 0, "y": 0.590}, "target" : {"x": 2, "y": 0.1066} },
{ "source": {"x": 0, "y": 0.921}, "target" : {"x": 2, "y": 0.1300} },
{ "source": {"x": 0, "y": 0.921}, "target" : {"x": 2, "y": 0.1517} },
{ "source": {"x": 0, "y": 0.1257}, "target" : {"x": 2, "y": 0.1359} },
{ "source": {"x": 0, "y": 0.423}, "target" : {"x": 2, "y": 0.1135} },
{ "source": {"x": 0, "y": 0.1169}, "target" : {"x": 2, "y": 0.1066} },
{ "source": {"x": 0, "y": 0.373}, "target" : {"x": 2, "y": 0.1415} },
{ "source": {"x": 0, "y": 0.25}, "target" : {"x": 2, "y": 0.21} },
{ "source": {"x": 0, "y": 0.19}, "target" : {"x": 2, "y": 0.21} },
{ "source": {"x": 0, "y": 0.683}, "target" : {"x": 2, "y": 0.772} },
{ "source": {"x": 0, "y": 0.683}, "target" : {"x": 2, "y": 0.791} },
{ "source": {"x": 0, "y": 0.683}, "target" : {"x": 2, "y": 0.844} },
{ "source": {"x": 0, "y": 0.460}, "target" : {"x": 2, "y": 0.410} },
{ "source": {"x": 0, "y": 0.1036}, "target" : {"x": 2, "y": 0.863} },
{ "source": {"x": 0, "y": 0.670}, "target" : {"x": 2, "y": 0.863} },
{ "source": {"x": 0, "y": 0.737}, "target" : {"x": 2, "y": 0.410} },
{ "source": {"x": 0, "y": 0.588}, "target" : {"x": 2, "y": 0.594} },
{ "source": {"x": 0, "y": 0.494}, "target" : {"x": 2, "y": 0.594} },
{ "source": {"x": 0, "y": 0.428}, "target" : {"x": 2, "y": 0.594} },
{ "source": {"x": 0, "y": 0.736}, "target" : {"x": 2, "y": 0.989} },
{ "source": {"x": 0, "y": 0.780}, "target" : {"x": 2, "y": 0.823} },
{ "source": {"x": 0, "y": 0.584}, "target" : {"x": 2, "y": 0.638} },
{ "source": {"x": 0, "y": 0.551}, "target" : {"x": 2, "y": 0.638} },
{ "source": {"x": 0, "y": 0.505}, "target" : {"x": 2, "y": 0.795} },
{ "source": {"x": 0, "y": 0.505}, "target" : {"x": 2, "y": 0.889} },
{ "source": {"x": 0, "y": 0.1028}, "target" : {"x": 2, "y": 0.72} },
{ "source": {"x": 0, "y": 0.309}, "target" : {"x": 2, "y": 0.361} },
{ "source": {"x": 0, "y": 0.379}, "target" : {"x": 2, "y": 0.361} },
{ "source": {"x": 0, "y": 0.535}, "target" : {"x": 2, "y": 0.1146} },
{ "source": {"x": 0, "y": 0.535}, "target" : {"x": 2, "y": 0.1033} },
{ "source": {"x": 0, "y": 0.1245}, "target" : {"x": 2, "y": 0.1509} },
{ "source": {"x": 0, "y": 0.536}, "target" : {"x": 2, "y": 0.864} },
{ "source": {"x": 1, "y": 0.114}, "target" : {"x": 0, "y": 0.474} },
{ "source": {"x": 1, "y": 0.49}, "target" : {"x": 0, "y": 0.186} },
{ "source": {"x": 1, "y": 0.231}, "target" : {"x": 0, "y": 0.1245} },
{ "source": {"x": 1, "y": 0.440}, "target" : {"x": 0, "y": 0.474} },
{ "source": {"x": 1, "y": 0.572}, "target" : {"x": 0, "y": 0.474} },
{ "source": {"x": 1, "y": 0.486}, "target" : {"x": 0, "y": 0.474} },
{ "source": {"x": 1, "y": 0.1170}, "target" : {"x": 0, "y": 0.904} },
{ "source": {"x": 1, "y": 0.1263}, "target" : {"x": 0, "y": 0.877} },
{ "source": {"x": 1, "y": 0.463}, "target" : {"x": 0, "y": 0.281} },
{ "source": {"x": 1, "y": 0.429}, "target" : {"x": 0, "y": 0.281} },
{ "source": {"x": 1, "y": 0.970}, "target" : {"x": 0, "y": 0.1069} },
{ "source": {"x": 1, "y": 0.362}, "target" : {"x": 0, "y": 0.386} },
{ "source": {"x": 1, "y": 0.1247}, "target" : {"x": 0, "y": 0.866} },
{ "source": {"x": 1, "y": 0.200}, "target" : {"x": 0, "y": 0.866} },
{ "source": {"x": 1, "y": 0.297}, "target" : {"x": 0, "y": 0.447} },
{ "source": {"x": 1, "y": 0.529}, "target" : {"x": 0, "y": 0.447} },
{ "source": {"x": 1, "y": 0.676}, "target" : {"x": 0, "y": 0.447} },
{ "source": {"x": 1, "y": 0.388}, "target" : {"x": 0, "y": 0.447} },
{ "source": {"x": 1, "y": 0.742}, "target" : {"x": 0, "y": 0.535} },
{ "source": {"x": 1, "y": 0.1001}, "target" : {"x": 0, "y": 0.1079} },
{ "source": {"x": 1, "y": 0.498}, "target" : {"x": 0, "y": 0.541} },
{ "source": {"x": 1, "y": 0.603}, "target" : {"x": 0, "y": 0.870} },
{ "source": {"x": 1, "y": 0.931}, "target" : {"x": 0, "y": 0.455} },
{ "source": {"x": 1, "y": 0.730}, "target" : {"x": 0, "y": 0.309} },
{ "source": {"x": 1, "y": 0.279}, "target" : {"x": 0, "y": 0.877} },
{ "source": {"x": 1, "y": 0.336}, "target" : {"x": 0, "y": 0.176} },
{ "source": {"x": 1, "y": 0.779}, "target" : {"x": 0, "y": 0.1155} },
{ "source": {"x": 1, "y": 0.779}, "target" : {"x": 0, "y": 0.1280} },
{ "source": {"x": 1, "y": 0.718}, "target" : {"x": 0, "y": 0.571} },
{ "source": {"x": 1, "y": 0.718}, "target" : {"x": 0, "y": 0.652} },
{ "source": {"x": 1, "y": 0.718}, "target" : {"x": 0, "y": 0.712} },
{ "source": {"x": 1, "y": 0.637}, "target" : {"x": 0, "y": 0.568} },
{ "source": {"x": 1, "y": 0.637}, "target" : {"x": 0, "y": 0.793} },
{ "source": {"x": 1, "y": 0.974}, "target" : {"x": 0, "y": 0.568} },
{ "source": {"x": 1, "y": 0.412}, "target" : {"x": 0, "y": 0.568} },
{ "source": {"x": 1, "y": 0.58}, "target" : {"x": 0, "y": 0.136} },
{ "source": {"x": 1, "y": 0.73}, "target" : {"x": 0, "y": 0.136} },
{ "source": {"x": 1, "y": 0.59}, "target" : {"x": 0, "y": 0.136} },
{ "source": {"x": 1, "y": 0.94}, "target" : {"x": 0, "y": 0.136} },
{ "source": {"x": 1, "y": 0.85}, "target" : {"x": 0, "y": 0.136} },
{ "source": {"x": 1, "y": 0.107}, "target" : {"x": 0, "y": 0.136} },
{ "source": {"x": 1, "y": 0.101}, "target" : {"x": 0, "y": 0.136} },
{ "source": {"x": 1, "y": 0.129}, "target" : {"x": 0, "y": 0.136} },
{ "source": {"x": 1, "y": 0.55}, "target" : {"x": 0, "y": 0.136} },
{ "source": {"x": 1, "y": 0.973}, "target" : {"x": 0, "y": 0.561} },
{ "source": {"x": 1, "y": 0.42}, "target" : {"x": 0, "y": 0.313} },
{ "source": {"x": 1, "y": 0.44}, "target" : {"x": 0, "y": 0.305} },
{ "source": {"x": 1, "y": 0.44}, "target" : {"x": 0, "y": 0.186} },
{ "source": {"x": 1, "y": 0.123}, "target" : {"x": 0, "y": 0.166} },
{ "source": {"x": 1, "y": 0.1250}, "target" : {"x": 0, "y": 0.1184} },
{ "source": {"x": 1, "y": 0.237}, "target" : {"x": 0, "y": 0.728} },
{ "source": {"x": 1, "y": 0.237}, "target" : {"x": 0, "y": 0.612} },
{ "source": {"x": 1, "y": 0.757}, "target" : {"x": 0, "y": 0.612} },
{ "source": {"x": 1, "y": 0.757}, "target" : {"x": 0, "y": 0.428} },
{ "source": {"x": 1, "y": 0.661}, "target" : {"x": 0, "y": 0.612} },
{ "source": {"x": 1, "y": 0.1284}, "target" : {"x": 0, "y": 0.921} },
{ "source": {"x": 1, "y": 0.938}, "target" : {"x": 0, "y": 0.308} },
{ "source": {"x": 1, "y": 0.396}, "target" : {"x": 0, "y": 0.305} },
{ "source": {"x": 1, "y": 0.396}, "target" : {"x": 0, "y": 0.191} },
{ "source": {"x": 1, "y": 0.396}, "target" : {"x": 0, "y": 0.281} },
{ "source": {"x": 1, "y": 0.744}, "target" : {"x": 0, "y": 0.305} },
{ "source": {"x": 1, "y": 0.744}, "target" : {"x": 0, "y": 0.191} },
{ "source": {"x": 1, "y": 0.448}, "target" : {"x": 0, "y": 0.305} },
{ "source": {"x": 1, "y": 0.448}, "target" : {"x": 0, "y": 0.191} },
{ "source": {"x": 1, "y": 0.927}, "target" : {"x": 0, "y": 0.590} },
{ "source": {"x": 1, "y": 0.832}, "target" : {"x": 0, "y": 0.176} },
{ "source": {"x": 1, "y": 0.832}, "target" : {"x": 0, "y": 0.728} },
{ "source": {"x": 1, "y": 0.340}, "target" : {"x": 0, "y": 0.176} },
{ "source": {"x": 1, "y": 0.312}, "target" : {"x": 0, "y": 0.176} },
{ "source": {"x": 1, "y": 0.209}, "target" : {"x": 0, "y": 0.176} },
{ "source": {"x": 1, "y": 0.1208}, "target" : {"x": 0, "y": 0.1257} },
{ "source": {"x": 1, "y": 0.334}, "target" : {"x": 0, "y": 0.386} },
{ "source": {"x": 1, "y": 0.334}, "target" : {"x": 0, "y": 0.510} },
{ "source": {"x": 1, "y": 0.643}, "target" : {"x": 0, "y": 0.386} },
{ "source": {"x": 1, "y": 0.643}, "target" : {"x": 0, "y": 0.510} },
{ "source": {"x": 1, "y": 0.149}, "target" : {"x": 0, "y": 0.386} },
{ "source": {"x": 1, "y": 0.149}, "target" : {"x": 0, "y": 0.510} },
{ "source": {"x": 1, "y": 0.959}, "target" : {"x": 0, "y": 0.1186} },
{ "source": {"x": 1, "y": 0.366}, "target" : {"x": 0, "y": 0.783} },
{ "source": {"x": 1, "y": 0.366}, "target" : {"x": 0, "y": 0.1160} },
{ "source": {"x": 1, "y": 0.722}, "target" : {"x": 0, "y": 0.345} },
{ "source": {"x": 1, "y": 0.640}, "target" : {"x": 0, "y": 0.499} },
{ "source": {"x": 1, "y": 0.549}, "target" : {"x": 0, "y": 0.499} },
{ "source": {"x": 1, "y": 0.477}, "target" : {"x": 0, "y": 0.499} },
{ "source": {"x": 1, "y": 0.1056}, "target" : {"x": 0, "y": 0.1159} },
{ "source": {"x": 1, "y": 0.1056}, "target" : {"x": 0, "y": 0.1009} },
{ "source": {"x": 1, "y": 0.177}, "target" : {"x": 0, "y": 0.186} },
{ "source": {"x": 1, "y": 0.95}, "target" : {"x": 0, "y": 0.186} },
{ "source": {"x": 1, "y": 0.249}, "target" : {"x": 0, "y": 0.186} },
{ "source": {"x": 1, "y": 0.483}, "target" : {"x": 0, "y": 0.373} },
{ "source": {"x": 1, "y": 0.483}, "target" : {"x": 0, "y": 0.321} },
{ "source": {"x": 1, "y": 0.483}, "target" : {"x": 0, "y": 0.532} },
{ "source": {"x": 1, "y": 0.483}, "target" : {"x": 0, "y": 0.629} },
{ "source": {"x": 1, "y": 0.707}, "target" : {"x": 0, "y": 0.923} },
{ "source": {"x": 1, "y": 0.6}, "target" : {"x": 0, "y": 0.19} },
{ "source": {"x": 1, "y": 0.6}, "target" : {"x": 0, "y": 0.25} },
{ "source": {"x": 1, "y": 0.10}, "target" : {"x": 0, "y": 0.19} },
{ "source": {"x": 1, "y": 0.10}, "target" : {"x": 0, "y": 0.25} },
{ "source": {"x": 1, "y": 0.8}, "target" : {"x": 0, "y": 0.19} },
{ "source": {"x": 1, "y": 0.8}, "target" : {"x": 0, "y": 0.25} },
{ "source": {"x": 1, "y": 0.12}, "target" : {"x": 0, "y": 0.19} },
{ "source": {"x": 1, "y": 0.12}, "target" : {"x": 0, "y": 0.25} },
{ "source": {"x": 1, "y": 0.24}, "target" : {"x": 0, "y": 0.19} },
{ "source": {"x": 1, "y": 0.24}, "target" : {"x": 0, "y": 0.25} },
{ "source": {"x": 1, "y": 0.14}, "target" : {"x": 0, "y": 0.19} },
{ "source": {"x": 1, "y": 0.14}, "target" : {"x": 0, "y": 0.25} },
{ "source": {"x": 1, "y": 0.26}, "target" : {"x": 0, "y": 0.19} },
{ "source": {"x": 1, "y": 0.26}, "target" : {"x": 0, "y": 0.25} },
{ "source": {"x": 1, "y": 0.22}, "target" : {"x": 0, "y": 0.25} },
{ "source": {"x": 1, "y": 0.22}, "target" : {"x": 0, "y": 0.19} },
{ "source": {"x": 1, "y": 0.11}, "target" : {"x": 0, "y": 0.25} },
{ "source": {"x": 1, "y": 0.11}, "target" : {"x": 0, "y": 0.19} },
{ "source": {"x": 1, "y": 0.15}, "target" : {"x": 0, "y": 0.25} },
{ "source": {"x": 1, "y": 0.15}, "target" : {"x": 0, "y": 0.19} },
{ "source": {"x": 1, "y": 0.7}, "target" : {"x": 0, "y": 0.19} },
{ "source": {"x": 1, "y": 0.7}, "target" : {"x": 0, "y": 0.25} },
{ "source": {"x": 1, "y": 0.16}, "target" : {"x": 0, "y": 0.19} },
{ "source": {"x": 1, "y": 0.16}, "target" : {"x": 0, "y": 0.25} },
{ "source": {"x": 1, "y": 0.20}, "target" : {"x": 0, "y": 0.19} },
{ "source": {"x": 1, "y": 0.20}, "target" : {"x": 0, "y": 0.25} },
{ "source": {"x": 1, "y": 0.27}, "target" : {"x": 0, "y": 0.19} },
{ "source": {"x": 1, "y": 0.27}, "target" : {"x": 0, "y": 0.25} },
{ "source": {"x": 1, "y": 0.17}, "target" : {"x": 0, "y": 0.19} },
{ "source": {"x": 1, "y": 0.17}, "target" : {"x": 0, "y": 0.25} },
{ "source": {"x": 1, "y": 0.5}, "target" : {"x": 0, "y": 0.19} },
{ "source": {"x": 1, "y": 0.5}, "target" : {"x": 0, "y": 0.25} },
{ "source": {"x": 1, "y": 0.1237}, "target" : {"x": 0, "y": 0.1048} },
{ "source": {"x": 1, "y": 0.839}, "target" : {"x": 0, "y": 0.1048} },
{ "source": {"x": 1, "y": 0.416}, "target" : {"x": 0, "y": 0.737} },
{ "source": {"x": 1, "y": 0.416}, "target" : {"x": 0, "y": 0.460} },
{ "source": {"x": 1, "y": 0.1118}, "target" : {"x": 0, "y": 0.460} },
{ "source": {"x": 1, "y": 0.217}, "target" : {"x": 0, "y": 0.541} },
{ "source": {"x": 1, "y": 0.465}, "target" : {"x": 0, "y": 0.541} },
{ "source": {"x": 1, "y": 0.657}, "target" : {"x": 0, "y": 0.460} },
{ "source": {"x": 1, "y": 0.657}, "target" : {"x": 0, "y": 0.737} },
{ "source": {"x": 1, "y": 0.578}, "target" : {"x": 0, "y": 0.689} },
{ "source": {"x": 1, "y": 0.338}, "target" : {"x": 0, "y": 0.689} },
{ "source": {"x": 1, "y": 0.338}, "target" : {"x": 0, "y": 0.584} },
{ "source": {"x": 1, "y": 0.401}, "target" : {"x": 0, "y": 0.689} },
{ "source": {"x": 1, "y": 0.602}, "target" : {"x": 0, "y": 0.912} },
{ "source": {"x": 1, "y": 0.738}, "target" : {"x": 0, "y": 0.912} },
{ "source": {"x": 1, "y": 0.803}, "target" : {"x": 0, "y": 0.912} },
{ "source": {"x": 1, "y": 0.815}, "target" : {"x": 0, "y": 0.612} },
{ "source": {"x": 1, "y": 0.509}, "target" : {"x": 0, "y": 0.428} },
{ "source": {"x": 1, "y": 0.509}, "target" : {"x": 0, "y": 0.494} },
{ "source": {"x": 1, "y": 0.509}, "target" : {"x": 0, "y": 0.588} },
{ "source": {"x": 1, "y": 0.1077}, "target" : {"x": 0, "y": 0.417} },
{ "source": {"x": 1, "y": 0.332}, "target" : {"x": 0, "y": 0.1442} },
{ "source": {"x": 1, "y": 0.190}, "target" : {"x": 0, "y": 0.571} },
{ "source": {"x": 1, "y": 0.190}, "target" : {"x": 0, "y": 0.652} },
{ "source": {"x": 1, "y": 0.190}, "target" : {"x": 0, "y": 0.712} },
{ "source": {"x": 1, "y": 0.190}, "target" : {"x": 0, "y": 0.736} },
{ "source": {"x": 1, "y": 0.642}, "target" : {"x": 0, "y": 0.736} },
{ "source": {"x": 1, "y": 0.850}, "target" : {"x": 0, "y": 0.736} },
{ "source": {"x": 1, "y": 0.900}, "target" : {"x": 0, "y": 0.568} },
{ "source": {"x": 1, "y": 0.822}, "target" : {"x": 0, "y": 0.904} },
{ "source": {"x": 1, "y": 0.133}, "target" : {"x": 0, "y": 0.584} },
{ "source": {"x": 1, "y": 0.133}, "target" : {"x": 0, "y": 0.551} },
{ "source": {"x": 1, "y": 0.48}, "target" : {"x": 0, "y": 0.561} },
{ "source": {"x": 1, "y": 0.48}, "target" : {"x": 0, "y": 0.281} },
{ "source": {"x": 1, "y": 0.69}, "target" : {"x": 0, "y": 0.281} },
{ "source": {"x": 1, "y": 0.31}, "target" : {"x": 0, "y": 0.499} },
{ "source": {"x": 1, "y": 0.188}, "target" : {"x": 0, "y": 0.689} },
{ "source": {"x": 1, "y": 0.1229}, "target" : {"x": 0, "y": 0.1426} },
{ "source": {"x": 1, "y": 0.222}, "target" : {"x": 0, "y": 0.585} },
{ "source": {"x": 1, "y": 0.755}, "target" : {"x": 0, "y": 0.728} },
{ "source": {"x": 1, "y": 0.520}, "target" : {"x": 0, "y": 0.1100} },
{ "source": {"x": 1, "y": 0.788}, "target" : {"x": 0, "y": 0.870} },
{ "source": {"x": 1, "y": 0.122}, "target" : {"x": 0, "y": 0.670} },
{ "source": {"x": 1, "y": 0.122}, "target" : {"x": 0, "y": 0.793} },
{ "source": {"x": 1, "y": 0.316}, "target" : {"x": 0, "y": 0.1028} },
{ "source": {"x": 1, "y": 0.316}, "target" : {"x": 0, "y": 0.623} },
{ "source": {"x": 1, "y": 0.51}, "target" : {"x": 0, "y": 0.623} },
{ "source": {"x": 1, "y": 0.765}, "target" : {"x": 0, "y": 0.610} },
{ "source": {"x": 1, "y": 0.470}, "target" : {"x": 0, "y": 0.444} },
{ "source": {"x": 1, "y": 0.470}, "target" : {"x": 0, "y": 0.508} },
{ "source": {"x": 1, "y": 0.470}, "target" : {"x": 0, "y": 0.610} },
{ "source": {"x": 1, "y": 0.29}, "target" : {"x": 0, "y": 0.186} },
{ "source": {"x": 1, "y": 0.459}, "target" : {"x": 0, "y": 0.1520} },
{ "source": {"x": 1, "y": 0.459}, "target" : {"x": 0, "y": 0.541} },
{ "source": {"x": 1, "y": 0.1210}, "target" : {"x": 0, "y": 0.510} },
{ "source": {"x": 1, "y": 0.471}, "target" : {"x": 0, "y": 0.812} },
{ "source": {"x": 1, "y": 0.54}, "target" : {"x": 0, "y": 0.551} },
{ "source": {"x": 1, "y": 0.54}, "target" : {"x": 0, "y": 0.561} },
{ "source": {"x": 1, "y": 0.218}, "target" : {"x": 0, "y": 0.623} },
{ "source": {"x": 1, "y": 0.394}, "target" : {"x": 0, "y": 0.1186} },
{ "source": {"x": 1, "y": 0.53}, "target" : {"x": 0, "y": 0.505} },
{ "source": {"x": 1, "y": 0.53}, "target" : {"x": 0, "y": 0.186} },
{ "source": {"x": 1, "y": 0.331}, "target" : {"x": 0, "y": 0.367} },
{ "source": {"x": 1, "y": 0.331}, "target" : {"x": 0, "y": 0.308} },
{ "source": {"x": 1, "y": 0.331}, "target" : {"x": 0, "y": 0.1423} },
{ "source": {"x": 1, "y": 0.331}, "target" : {"x": 0, "y": 0.384} },
{ "source": {"x": 1, "y": 0.331}, "target" : {"x": 0, "y": 0.457} },
{ "source": {"x": 1, "y": 0.255}, "target" : {"x": 0, "y": 0.384} },
{ "source": {"x": 1, "y": 0.255}, "target" : {"x": 0, "y": 0.457} },
{ "source": {"x": 1, "y": 0.255}, "target" : {"x": 0, "y": 0.367} },
{ "source": {"x": 1, "y": 0.255}, "target" : {"x": 0, "y": 0.308} },
{ "source": {"x": 1, "y": 0.43}, "target" : {"x": 0, "y": 0.499} },
{ "source": {"x": 1, "y": 0.414}, "target" : {"x": 0, "y": 0.444} },
{ "source": {"x": 1, "y": 0.414}, "target" : {"x": 0, "y": 0.508} },
{ "source": {"x": 1, "y": 0.895}, "target" : {"x": 0, "y": 0.675} },
{ "source": {"x": 1, "y": 0.740}, "target" : {"x": 0, "y": 0.698} },
{ "source": {"x": 1, "y": 0.563}, "target" : {"x": 0, "y": 0.287} },
{ "source": {"x": 1, "y": 0.303}, "target" : {"x": 0, "y": 0.379} },
{ "source": {"x": 1, "y": 0.303}, "target" : {"x": 0, "y": 0.309} },
{ "source": {"x": 1, "y": 0.478}, "target" : {"x": 0, "y": 0.379} },
{ "source": {"x": 1, "y": 0.478}, "target" : {"x": 0, "y": 0.309} },
{ "source": {"x": 1, "y": 0.719}, "target" : {"x": 0, "y": 0.379} },
{ "source": {"x": 1, "y": 0.702}, "target" : {"x": 0, "y": 0.698} },
{ "source": {"x": 1, "y": 0.490}, "target" : {"x": 0, "y": 0.877} },
{ "source": {"x": 1, "y": 0.476}, "target" : {"x": 0, "y": 0.753} },
{ "source": {"x": 1, "y": 0.1142}, "target" : {"x": 0, "y": 0.753} },
{ "source": {"x": 1, "y": 0.1204}, "target" : {"x": 0, "y": 0.505} },
{ "source": {"x": 1, "y": 0.454}, "target" : {"x": 0, "y": 0.1079} },
{ "source": {"x": 1, "y": 0.1132}, "target" : {"x": 0, "y": 0.1319} },
{ "source": {"x": 1, "y": 0.435}, "target" : {"x": 0, "y": 0.1009} },
{ "source": {"x": 1, "y": 0.435}, "target" : {"x": 0, "y": 0.675} },
{ "source": {"x": 1, "y": 0.435}, "target" : {"x": 0, "y": 0.1034} },
{ "source": {"x": 1, "y": 0.435}, "target" : {"x": 0, "y": 0.857} },
{ "source": {"x": 1, "y": 0.920}, "target" : {"x": 0, "y": 0.753} },
{ "source": {"x": 1, "y": 0.256}, "target" : {"x": 0, "y": 0.585} },
{ "source": {"x": 1, "y": 0.256}, "target" : {"x": 0, "y": 0.683} },
{ "source": {"x": 1, "y": 0.681}, "target" : {"x": 0, "y": 0.585} },
{ "source": {"x": 1, "y": 0.1017}, "target" : {"x": 0, "y": 0.447} },
{ "source": {"x": 1, "y": 0.18}, "target" : {"x": 0, "y": 0.19} },
{ "source": {"x": 1, "y": 0.18}, "target" : {"x": 0, "y": 0.25} },
{ "source": {"x": 1, "y": 0.295}, "target" : {"x": 0, "y": 0.1100} },
{ "source": {"x": 2, "y": 0.988}, "target" : {"x": 1, "y": 0.31} },
{ "source": {"x": 2, "y": 0.636}, "target" : {"x": 1, "y": 0.31} },
{ "source": {"x": 2, "y": 0.636}, "target" : {"x": 1, "y": 0.47} },
{ "source": {"x": 2, "y": 0.818}, "target" : {"x": 1, "y": 0.31} },
{ "source": {"x": 2, "y": 0.1356}, "target" : {"x": 1, "y": 0.981} },
{ "source": {"x": 2, "y": 0.1047}, "target" : {"x": 1, "y": 0.69} },
{ "source": {"x": 2, "y": 0.1047}, "target" : {"x": 1, "y": 0.320} },
{ "source": {"x": 2, "y": 0.1162}, "target" : {"x": 1, "y": 0.390} },
{ "source": {"x": 2, "y": 0.1162}, "target" : {"x": 1, "y": 0.522} },
{ "source": {"x": 2, "y": 0.1287}, "target" : {"x": 1, "y": 0.432} },
{ "source": {"x": 2, "y": 0.1183}, "target" : {"x": 1, "y": 0.970} },
{ "source": {"x": 2, "y": 0.556}, "target" : {"x": 1, "y": 0.57} },
{ "source": {"x": 2, "y": 0.556}, "target" : {"x": 1, "y": 0.347} },
{ "source": {"x": 2, "y": 0.556}, "target" : {"x": 1, "y": 0.622} },
{ "source": {"x": 2, "y": 0.556}, "target" : {"x": 1, "y": 0.475} },
{ "source": {"x": 2, "y": 0.251}, "target" : {"x": 1, "y": 0.168} },
{ "source": {"x": 2, "y": 0.251}, "target" : {"x": 1, "y": 0.276} },
{ "source": {"x": 2, "y": 0.251}, "target" : {"x": 1, "y": 0.244} },
{ "source": {"x": 2, "y": 0.251}, "target" : {"x": 1, "y": 0.272} },
{ "source": {"x": 2, "y": 0.251}, "target" : {"x": 1, "y": 0.263} },
{ "source": {"x": 2, "y": 0.418}, "target" : {"x": 1, "y": 0.276} },
{ "source": {"x": 2, "y": 0.418}, "target" : {"x": 1, "y": 0.244} },
{ "source": {"x": 2, "y": 0.418}, "target" : {"x": 1, "y": 0.272} },
{ "source": {"x": 2, "y": 0.398}, "target" : {"x": 1, "y": 0.244} },
{ "source": {"x": 2, "y": 0.398}, "target" : {"x": 1, "y": 0.272} },
{ "source": {"x": 2, "y": 0.398}, "target" : {"x": 1, "y": 0.276} },
{ "source": {"x": 2, "y": 0.484}, "target" : {"x": 1, "y": 0.13} },
{ "source": {"x": 2, "y": 0.484}, "target" : {"x": 1, "y": 0.91} },
{ "source": {"x": 2, "y": 0.484}, "target" : {"x": 1, "y": 0.77} },
{ "source": {"x": 2, "y": 0.484}, "target" : {"x": 1, "y": 0.125} },
{ "source": {"x": 2, "y": 0.484}, "target" : {"x": 1, "y": 0.929} },
{ "source": {"x": 2, "y": 0.841}, "target" : {"x": 1, "y": 0.407} },
{ "source": {"x": 2, "y": 0.841}, "target" : {"x": 1, "y": 0.975} },
{ "source": {"x": 2, "y": 0.841}, "target" : {"x": 1, "y": 0.362} },
{ "source": {"x": 2, "y": 0.96}, "target" : {"x": 1, "y": 0.102} },
{ "source": {"x": 2, "y": 0.96}, "target" : {"x": 1, "y": 0.118} },
{ "source": {"x": 2, "y": 0.96}, "target" : {"x": 1, "y": 0.93} },
{ "source": {"x": 2, "y": 0.96}, "target" : {"x": 1, "y": 0.80} },
{ "source": {"x": 2, "y": 0.96}, "target" : {"x": 1, "y": 0.84} },
{ "source": {"x": 2, "y": 0.96}, "target" : {"x": 1, "y": 0.141} },
{ "source": {"x": 2, "y": 0.96}, "target" : {"x": 1, "y": 0.142} },
{ "source": {"x": 2, "y": 0.96}, "target" : {"x": 1, "y": 0.108} },
{ "source": {"x": 2, "y": 0.96}, "target" : {"x": 1, "y": 0.127} },
{ "source": {"x": 2, "y": 0.1233}, "target" : {"x": 1, "y": 0.533} },
{ "source": {"x": 2, "y": 0.739}, "target" : {"x": 1, "y": 0.117} },
{ "source": {"x": 2, "y": 0.939}, "target" : {"x": 1, "y": 0.959} },
{ "source": {"x": 2, "y": 0.582}, "target" : {"x": 1, "y": 0.491} },
{ "source": {"x": 2, "y": 0.582}, "target" : {"x": 1, "y": 0.426} },
{ "source": {"x": 2, "y": 0.582}, "target" : {"x": 1, "y": 0.335} },
{ "source": {"x": 2, "y": 0.598}, "target" : {"x": 1, "y": 0.491} },
{ "source": {"x": 2, "y": 0.598}, "target" : {"x": 1, "y": 0.426} },
{ "source": {"x": 2, "y": 0.598}, "target" : {"x": 1, "y": 0.335} },
{ "source": {"x": 2, "y": 0.926}, "target" : {"x": 1, "y": 0.534} },
{ "source": {"x": 2, "y": 0.382}, "target" : {"x": 1, "y": 0.66} },
{ "source": {"x": 2, "y": 0.382}, "target" : {"x": 1, "y": 0.71} },
{ "source": {"x": 2, "y": 0.382}, "target" : {"x": 1, "y": 0.65} },
{ "source": {"x": 2, "y": 0.382}, "target" : {"x": 1, "y": 0.88} },
{ "source": {"x": 2, "y": 0.382}, "target" : {"x": 1, "y": 0.501} },
{ "source": {"x": 2, "y": 0.761}, "target" : {"x": 1, "y": 0.163} },
{ "source": {"x": 2, "y": 0.980}, "target" : {"x": 1, "y": 0.311} },
{ "source": {"x": 2, "y": 0.1103}, "target" : {"x": 1, "y": 0.730} },
{ "source": {"x": 2, "y": 0.1173}, "target" : {"x": 1, "y": 0.730} },
{ "source": {"x": 2, "y": 0.1149}, "target" : {"x": 1, "y": 0.755} },
{ "source": {"x": 2, "y": 0.493}, "target" : {"x": 1, "y": 0.232} },
{ "source": {"x": 2, "y": 0.493}, "target" : {"x": 1, "y": 0.1168} },
{ "source": {"x": 2, "y": 0.908}, "target" : {"x": 1, "y": 0.82} },
{ "source": {"x": 2, "y": 0.908}, "target" : {"x": 1, "y": 0.349} },
{ "source": {"x": 2, "y": 0.908}, "target" : {"x": 1, "y": 0.1019} },
{ "source": {"x": 2, "y": 0.710}, "target" : {"x": 1, "y": 0.550} },
{ "source": {"x": 2, "y": 0.710}, "target" : {"x": 1, "y": 0.1010} },
{ "source": {"x": 2, "y": 0.710}, "target" : {"x": 1, "y": 0.296} },
{ "source": {"x": 2, "y": 0.710}, "target" : {"x": 1, "y": 0.815} },
{ "source": {"x": 2, "y": 0.205}, "target" : {"x": 1, "y": 0.13} },
{ "source": {"x": 2, "y": 0.205}, "target" : {"x": 1, "y": 0.91} },
{ "source": {"x": 2, "y": 0.205}, "target" : {"x": 1, "y": 0.125} },
{ "source": {"x": 2, "y": 0.205}, "target" : {"x": 1, "y": 0.77} },
{ "source": {"x": 2, "y": 0.205}, "target" : {"x": 1, "y": 0.150} },
{ "source": {"x": 2, "y": 0.205}, "target" : {"x": 1, "y": 0.116} },
{ "source": {"x": 2, "y": 0.205}, "target" : {"x": 1, "y": 0.134} },
{ "source": {"x": 2, "y": 0.1249}, "target" : {"x": 1, "y": 0.405} },
{ "source": {"x": 2, "y": 0.1431}, "target" : {"x": 1, "y": 0.525} },
{ "source": {"x": 2, "y": 0.775}, "target" : {"x": 1, "y": 0.953} },
{ "source": {"x": 2, "y": 0.1176}, "target" : {"x": 1, "y": 0.953} },
{ "source": {"x": 2, "y": 0.1161}, "target" : {"x": 1, "y": 0.1138} },
{ "source": {"x": 2, "y": 0.480}, "target" : {"x": 1, "y": 0.434} },
{ "source": {"x": 2, "y": 0.1479}, "target" : {"x": 1, "y": 0.261} },
{ "source": {"x": 2, "y": 0.1325}, "target" : {"x": 1, "y": 0.829} },
{ "source": {"x": 2, "y": 0.933}, "target" : {"x": 1, "y": 0.829} },
{ "source": {"x": 2, "y": 0.1035}, "target" : {"x": 1, "y": 0.1008} },
{ "source": {"x": 2, "y": 0.1035}, "target" : {"x": 1, "y": 0.609} },
{ "source": {"x": 2, "y": 0.202}, "target" : {"x": 1, "y": 0.46} },
{ "source": {"x": 2, "y": 0.202}, "target" : {"x": 1, "y": 0.159} },
{ "source": {"x": 2, "y": 0.202}, "target" : {"x": 1, "y": 0.238} },
{ "source": {"x": 2, "y": 0.202}, "target" : {"x": 1, "y": 0.145} },
{ "source": {"x": 2, "y": 0.202}, "target" : {"x": 1, "y": 0.36} },
{ "source": {"x": 2, "y": 0.202}, "target" : {"x": 1, "y": 0.30} },
{ "source": {"x": 2, "y": 0.202}, "target" : {"x": 1, "y": 0.28} },
{ "source": {"x": 2, "y": 0.950}, "target" : {"x": 1, "y": 0.64} },
{ "source": {"x": 2, "y": 0.1378}, "target" : {"x": 1, "y": 0.174} },
{ "source": {"x": 2, "y": 0.1255}, "target" : {"x": 1, "y": 0.927} },
{ "source": {"x": 2, "y": 0.1300}, "target" : {"x": 1, "y": 0.647} },
{ "source": {"x": 2, "y": 0.1373}, "target" : {"x": 1, "y": 0.632} },
{ "source": {"x": 2, "y": 0.275}, "target" : {"x": 1, "y": 0.336} },
{ "source": {"x": 2, "y": 0.275}, "target" : {"x": 1, "y": 0.209} },
{ "source": {"x": 2, "y": 0.275}, "target" : {"x": 1, "y": 0.312} },
{ "source": {"x": 2, "y": 0.275}, "target" : {"x": 1, "y": 0.340} },
{ "source": {"x": 2, "y": 0.1496}, "target" : {"x": 1, "y": 0.469} },
{ "source": {"x": 2, "y": 0.1267}, "target" : {"x": 1, "y": 0.855} },
{ "source": {"x": 2, "y": 0.1487}, "target" : {"x": 1, "y": 0.731} },
{ "source": {"x": 2, "y": 0.1088}, "target" : {"x": 1, "y": 0.743} },
{ "source": {"x": 2, "y": 0.1401}, "target" : {"x": 1, "y": 0.749} },
{ "source": {"x": 2, "y": 0.1467}, "target" : {"x": 1, "y": 0.58} },
{ "source": {"x": 2, "y": 0.616}, "target" : {"x": 1, "y": 0.232} },
{ "source": {"x": 2, "y": 0.616}, "target" : {"x": 1, "y": 0.468} },
{ "source": {"x": 2, "y": 0.1039}, "target" : {"x": 1, "y": 0.232} },
{ "source": {"x": 2, "y": 0.365}, "target" : {"x": 1, "y": 0.897} },
{ "source": {"x": 2, "y": 0.365}, "target" : {"x": 1, "y": 0.954} },
{ "source": {"x": 2, "y": 0.365}, "target" : {"x": 1, "y": 0.147} },
{ "source": {"x": 2, "y": 0.365}, "target" : {"x": 1, "y": 0.567} },
{ "source": {"x": 2, "y": 0.365}, "target" : {"x": 1, "y": 0.270} },
{ "source": {"x": 2, "y": 0.990}, "target" : {"x": 1, "y": 0.11} },
{ "source": {"x": 2, "y": 0.21}, "target" : {"x": 1, "y": 0.17} },
{ "source": {"x": 2, "y": 0.21}, "target" : {"x": 1, "y": 0.27} },
{ "source": {"x": 2, "y": 0.21}, "target" : {"x": 1, "y": 0.20} },
{ "source": {"x": 2, "y": 0.21}, "target" : {"x": 1, "y": 0.16} },
{ "source": {"x": 2, "y": 0.21}, "target" : {"x": 1, "y": 0.7} },
{ "source": {"x": 2, "y": 0.21}, "target" : {"x": 1, "y": 0.15} },
{ "source": {"x": 2, "y": 0.21}, "target" : {"x": 1, "y": 0.11} },
{ "source": {"x": 2, "y": 0.21}, "target" : {"x": 1, "y": 0.22} },
{ "source": {"x": 2, "y": 0.21}, "target" : {"x": 1, "y": 0.26} },
{ "source": {"x": 2, "y": 0.21}, "target" : {"x": 1, "y": 0.14} },
{ "source": {"x": 2, "y": 0.21}, "target" : {"x": 1, "y": 0.24} },
{ "source": {"x": 2, "y": 0.21}, "target" : {"x": 1, "y": 0.12} },
{ "source": {"x": 2, "y": 0.21}, "target" : {"x": 1, "y": 0.8} },
{ "source": {"x": 2, "y": 0.21}, "target" : {"x": 1, "y": 0.10} },
{ "source": {"x": 2, "y": 0.21}, "target" : {"x": 1, "y": 0.18} },
{ "source": {"x": 2, "y": 0.21}, "target" : {"x": 1, "y": 0.6} },
{ "source": {"x": 2, "y": 0.21}, "target" : {"x": 1, "y": 0.5} },
{ "source": {"x": 2, "y": 0.864}, "target" : {"x": 1, "y": 0.226} },
{ "source": {"x": 2, "y": 0.479}, "target" : {"x": 1, "y": 0.264} },
{ "source": {"x": 2, "y": 0.479}, "target" : {"x": 1, "y": 0.315} },
{ "source": {"x": 2, "y": 0.409}, "target" : {"x": 1, "y": 0.264} },
{ "source": {"x": 2, "y": 0.409}, "target" : {"x": 1, "y": 0.315} },
{ "source": {"x": 2, "y": 0.518}, "target" : {"x": 1, "y": 0.264} },
{ "source": {"x": 2, "y": 0.518}, "target" : {"x": 1, "y": 0.315} },
{ "source": {"x": 2, "y": 0.391}, "target" : {"x": 1, "y": 0.315} },
{ "source": {"x": 2, "y": 0.391}, "target" : {"x": 1, "y": 0.264} },
{ "source": {"x": 2, "y": 0.410}, "target" : {"x": 1, "y": 0.416} },
{ "source": {"x": 2, "y": 0.410}, "target" : {"x": 1, "y": 0.657} },
{ "source": {"x": 2, "y": 0.504}, "target" : {"x": 1, "y": 0.385} },
{ "source": {"x": 2, "y": 0.504}, "target" : {"x": 1, "y": 0.450} },
{ "source": {"x": 2, "y": 0.504}, "target" : {"x": 1, "y": 0.346} },
{ "source": {"x": 2, "y": 0.504}, "target" : {"x": 1, "y": 0.70} },
{ "source": {"x": 2, "y": 0.504}, "target" : {"x": 1, "y": 0.292} },
{ "source": {"x": 2, "y": 0.1305}, "target" : {"x": 1, "y": 0.1189} },
{ "source": {"x": 2, "y": 0.1217}, "target" : {"x": 1, "y": 0.1144} },
{ "source": {"x": 2, "y": 0.1217}, "target" : {"x": 1, "y": 0.666} },
{ "source": {"x": 2, "y": 0.594}, "target" : {"x": 1, "y": 0.509} },
{ "source": {"x": 2, "y": 0.1181}, "target" : {"x": 1, "y": 0.89} },
{ "source": {"x": 2, "y": 0.1181}, "target" : {"x": 1, "y": 0.794} },
{ "source": {"x": 2, "y": 0.280}, "target" : {"x": 1, "y": 0.306} },
{ "source": {"x": 2, "y": 0.280}, "target" : {"x": 1, "y": 0.503} },
{ "source": {"x": 2, "y": 0.280}, "target" : {"x": 1, "y": 0.213} },
{ "source": {"x": 2, "y": 0.280}, "target" : {"x": 1, "y": 0.451} },
{ "source": {"x": 2, "y": 0.280}, "target" : {"x": 1, "y": 0.330} },
{ "source": {"x": 2, "y": 0.638}, "target" : {"x": 1, "y": 0.133} },
{ "source": {"x": 2, "y": 0.653}, "target" : {"x": 1, "y": 0.1} },
{ "source": {"x": 2, "y": 0.653}, "target" : {"x": 1, "y": 0.90} },
{ "source": {"x": 2, "y": 0.653}, "target" : {"x": 1, "y": 0.4} },
{ "source": {"x": 2, "y": 0.653}, "target" : {"x": 1, "y": 0.35} },
{ "source": {"x": 2, "y": 0.889}, "target" : {"x": 1, "y": 0.782} },
{ "source": {"x": 2, "y": 0.580}, "target" : {"x": 1, "y": 0.884} },
{ "source": {"x": 2, "y": 0.580}, "target" : {"x": 1, "y": 0.229} },
{ "source": {"x": 2, "y": 0.580}, "target" : {"x": 1, "y": 0.497} },
{ "source": {"x": 2, "y": 0.580}, "target" : {"x": 1, "y": 0.63} },
{ "source": {"x": 2, "y": 0.1049}, "target" : {"x": 1, "y": 0.630} },
{ "source": {"x": 2, "y": 0.1049}, "target" : {"x": 1, "y": 0.985} },
{ "source": {"x": 2, "y": 0.1338}, "target" : {"x": 1, "y": 0.284} },
{ "source": {"x": 2, "y": 0.1285}, "target" : {"x": 1, "y": 0.139} },
{ "source": {"x": 2, "y": 0.874}, "target" : {"x": 1, "y": 0.871} },
{ "source": {"x": 2, "y": 0.874}, "target" : {"x": 1, "y": 0.574} },
{ "source": {"x": 2, "y": 0.785}, "target" : {"x": 1, "y": 0.592} },
{ "source": {"x": 2, "y": 0.705}, "target" : {"x": 1, "y": 0.28} },
{ "source": {"x": 2, "y": 0.81}, "target" : {"x": 1, "y": 0.115} },
{ "source": {"x": 2, "y": 0.81}, "target" : {"x": 1, "y": 0.61} },
{ "source": {"x": 2, "y": 0.81}, "target" : {"x": 1, "y": 0.112} },
{ "source": {"x": 2, "y": 0.81}, "target" : {"x": 1, "y": 0.131} },
{ "source": {"x": 2, "y": 0.81}, "target" : {"x": 1, "y": 0.143} },
{ "source": {"x": 2, "y": 0.81}, "target" : {"x": 1, "y": 0.105} },
{ "source": {"x": 2, "y": 0.81}, "target" : {"x": 1, "y": 0.87} },
{ "source": {"x": 2, "y": 0.81}, "target" : {"x": 1, "y": 0.98} },
{ "source": {"x": 2, "y": 0.72}, "target" : {"x": 1, "y": 0.112} },
{ "source": {"x": 2, "y": 0.72}, "target" : {"x": 1, "y": 0.131} },
{ "source": {"x": 2, "y": 0.72}, "target" : {"x": 1, "y": 0.143} },
{ "source": {"x": 2, "y": 0.72}, "target" : {"x": 1, "y": 0.105} },
{ "source": {"x": 2, "y": 0.72}, "target" : {"x": 1, "y": 0.87} },
{ "source": {"x": 2, "y": 0.72}, "target" : {"x": 1, "y": 0.98} },
{ "source": {"x": 2, "y": 0.72}, "target" : {"x": 1, "y": 0.115} },
{ "source": {"x": 2, "y": 0.72}, "target" : {"x": 1, "y": 0.61} },
{ "source": {"x": 2, "y": 0.769}, "target" : {"x": 1, "y": 0.336} },
{ "source": {"x": 2, "y": 0.769}, "target" : {"x": 1, "y": 0.1307} },
{ "source": {"x": 2, "y": 0.1134}, "target" : {"x": 1, "y": 0.228} },
{ "source": {"x": 2, "y": 0.1031}, "target" : {"x": 1, "y": 0.862} },
{ "source": {"x": 2, "y": 0.183}, "target" : {"x": 1, "y": 0.33} },
{ "source": {"x": 2, "y": 0.183}, "target" : {"x": 1, "y": 0.218} },
{ "source": {"x": 2, "y": 0.183}, "target" : {"x": 1, "y": 0.182} },
{ "source": {"x": 2, "y": 0.183}, "target" : {"x": 1, "y": 0.310} },
{ "source": {"x": 2, "y": 0.183}, "target" : {"x": 1, "y": 0.263} },
{ "source": {"x": 2, "y": 0.183}, "target" : {"x": 1, "y": 0.162} },
{ "source": {"x": 2, "y": 0.679}, "target" : {"x": 1, "y": 0.749} },
{ "source": {"x": 2, "y": 0.679}, "target" : {"x": 1, "y": 0.284} },
{ "source": {"x": 2, "y": 0.679}, "target" : {"x": 1, "y": 0.696} },
{ "source": {"x": 2, "y": 0.679}, "target" : {"x": 1, "y": 0.316} },
{ "source": {"x": 2, "y": 0.978}, "target" : {"x": 1, "y": 0.317} },
{ "source": {"x": 2, "y": 0.827}, "target" : {"x": 1, "y": 0.317} },
{ "source": {"x": 2, "y": 0.1004}, "target" : {"x": 1, "y": 0.317} },
{ "source": {"x": 2, "y": 0.798}, "target" : {"x": 1, "y": 0.433} },
{ "source": {"x": 2, "y": 0.250}, "target" : {"x": 1, "y": 0.157} },
{ "source": {"x": 2, "y": 0.250}, "target" : {"x": 1, "y": 0.247} },
{ "source": {"x": 2, "y": 0.250}, "target" : {"x": 1, "y": 0.151} },
{ "source": {"x": 2, "y": 0.250}, "target" : {"x": 1, "y": 0.254} },
{ "source": {"x": 2, "y": 0.250}, "target" : {"x": 1, "y": 0.211} },
{ "source": {"x": 2, "y": 0.169}, "target" : {"x": 1, "y": 0.157} },
{ "source": {"x": 2, "y": 0.169}, "target" : {"x": 1, "y": 0.552} },
{ "source": {"x": 2, "y": 0.169}, "target" : {"x": 1, "y": 0.247} },
{ "source": {"x": 2, "y": 0.169}, "target" : {"x": 1, "y": 0.151} },
{ "source": {"x": 2, "y": 0.169}, "target" : {"x": 1, "y": 0.254} },
{ "source": {"x": 2, "y": 0.169}, "target" : {"x": 1, "y": 0.211} },
{ "source": {"x": 2, "y": 0.227}, "target" : {"x": 1, "y": 0.254} },
{ "source": {"x": 2, "y": 0.227}, "target" : {"x": 1, "y": 0.211} },
{ "source": {"x": 2, "y": 0.227}, "target" : {"x": 1, "y": 0.157} },
{ "source": {"x": 2, "y": 0.227}, "target" : {"x": 1, "y": 0.247} },
{ "source": {"x": 2, "y": 0.227}, "target" : {"x": 1, "y": 0.151} },
{ "source": {"x": 2, "y": 0.225}, "target" : {"x": 1, "y": 0.326} },
{ "source": {"x": 2, "y": 0.225}, "target" : {"x": 1, "y": 0.201} },
{ "source": {"x": 2, "y": 0.225}, "target" : {"x": 1, "y": 0.99} },
{ "source": {"x": 2, "y": 0.225}, "target" : {"x": 1, "y": 0.54} },
{ "source": {"x": 2, "y": 0.225}, "target" : {"x": 1, "y": 0.47} },
{ "source": {"x": 2, "y": 0.225}, "target" : {"x": 1, "y": 0.324} },
{ "source": {"x": 2, "y": 0.1054}, "target" : {"x": 1, "y": 0.619} },
{ "source": {"x": 2, "y": 0.361}, "target" : {"x": 1, "y": 0.303} },
{ "source": {"x": 2, "y": 0.361}, "target" : {"x": 1, "y": 0.478} },
{ "source": {"x": 2, "y": 0.1063}, "target" : {"x": 1, "y": 0.340} },
{ "source": {"x": 2, "y": 0.983}, "target" : {"x": 1, "y": 0.1299} },
{ "source": {"x": 2, "y": 0.878}, "target" : {"x": 1, "y": 0.272} },
{ "source": {"x": 2, "y": 0.887}, "target" : {"x": 1, "y": 0.537} },
{ "source": {"x": 2, "y": 0.1253}, "target" : {"x": 1, "y": 0.802} },
{ "source": {"x": 2, "y": 0.1253}, "target" : {"x": 1, "y": 0.1192} },
{ "source": {"x": 2, "y": 0.762}, "target" : {"x": 1, "y": 0.853} },
{ "source": {"x": 2, "y": 0.961}, "target" : {"x": 1, "y": 0.349} },
{ "source": {"x": 2, "y": 0.859}, "target" : {"x": 1, "y": 0.481} },
{ "source": {"x": 2, "y": 0.419}, "target" : {"x": 1, "y": 0.487} },
{ "source": {"x": 2, "y": 0.419}, "target" : {"x": 1, "y": 0.639} },
{ "source": {"x": 2, "y": 0.419}, "target" : {"x": 1, "y": 0.120} },
{ "source": {"x": 2, "y": 0.419}, "target" : {"x": 1, "y": 0.353} },
{ "source": {"x": 2, "y": 0.419}, "target" : {"x": 1, "y": 0.587} },
{ "source": {"x": 2, "y": 0.1235}, "target" : {"x": 1, "y": 0.6} },
{ "source": {"x": 2, "y": 0.1133}, "target" : {"x": 1, "y": 0.61} },
{ "source": {"x": 2, "y": 0.1311}, "target" : {"x": 1, "y": 0.721} },
{ "source": {"x": 2, "y": 0.693}, "target" : {"x": 1, "y": 0.872} },
{ "source": {"x": 2, "y": 0.1248}, "target" : {"x": 1, "y": 0.748} },
{ "source": {"x": 2, "y": 0.1248}, "target" : {"x": 1, "y": 0.235} },
{ "source": {"x": 2, "y": 0.967}, "target" : {"x": 1, "y": 0.987} },
{ "source": {"x": 2, "y": 0.1398}, "target" : {"x": 1, "y": 0.413} },
{ "source": {"x": 2, "y": 0.1200}, "target" : {"x": 1, "y": 0.16} },
{ "source": {"x": 2, "y": 0.1095}, "target" : {"x": 1, "y": 0.33} },
{ "source": {"x": 2, "y": 0.1095}, "target" : {"x": 1, "y": 0.756} },
{ "source": {"x": 2, "y": 0.290}, "target" : {"x": 1, "y": 0.645} },
{ "source": {"x": 2, "y": 0.290}, "target" : {"x": 1, "y": 0.339} },
{ "source": {"x": 2, "y": 0.1332}, "target" : {"x": 1, "y": 0.813} },
{ "source": {"x": 2, "y": 0.1332}, "target" : {"x": 1, "y": 0.1211} },
{ "source": {"x": 2, "y": 0.1438}, "target" : {"x": 1, "y": 0.59} },
{ "source": {"x": 2, "y": 0.678}, "target" : {"x": 1, "y": 0.252} },
{ "source": {"x": 2, "y": 0.678}, "target" : {"x": 1, "y": 0.38} },
{ "source": {"x": 2, "y": 0.678}, "target" : {"x": 1, "y": 0.138} },
{ "source": {"x": 2, "y": 0.1286}, "target" : {"x": 1, "y": 0.476} },
{ "source": {"x": 2, "y": 0.1179}, "target" : {"x": 1, "y": 0.32} },
{ "source": {"x": 2, "y": 0.1174}, "target" : {"x": 1, "y": 0.181} },
{ "source": {"x": 2, "y": 0.1174}, "target" : {"x": 1, "y": 0.156} },
{ "source": {"x": 2, "y": 0.566}, "target" : {"x": 1, "y": 0.234} }]